{
  "actions": [
    {
      "type": "alterTable",
      "alterTable": {
        "name": "ferramenta",
        "schema": "public",
        "addColumns": [],
        "deleteColumns": [],
        "modifyColumns": [
          {
            "columnName": "baseId",
            "addNullable": true,
            "removeNullable": false,
            "changeDefault": false
          },
          {
            "columnName": "veiculoId",
            "addNullable": true,
            "removeNullable": false,
            "changeDefault": false
          }
        ],
        "addIndexes": [],
        "deleteIndexes": [],
        "addForeignKeys": [],
        "deleteForeignKeys": [],
        "warnings": []
      }
    },
    {
      "type": "alterTable",
      "alterTable": {
        "name": "material",
        "schema": "public",
        "addColumns": [],
        "deleteColumns": [],
        "modifyColumns": [
          {
            "columnName": "baseId",
            "addNullable": true,
            "removeNullable": false,
            "changeDefault": false
          },
          {
            "columnName": "veiculoId",
            "addNullable": true,
            "removeNullable": false,
            "changeDefault": false
          }
        ],
        "addIndexes": [],
        "deleteIndexes": [],
        "addForeignKeys": [],
        "deleteForeignKeys": [],
        "warnings": []
      }
    },
    {
      "type": "alterTable",
      "alterTable": {
        "name": "movimentacao",
        "schema": "public",
        "addColumns": [],
        "deleteColumns": [],
        "modifyColumns": [
          {
            "columnName": "materialId",
            "addNullable": true,
            "removeNullable": false,
            "changeDefault": false
          },
          {
            "columnName": "ferramentaId",
            "addNullable": true,
            "removeNullable": false,
            "changeDefault": false
          },
          {
            "columnName": "origemBaseId",
            "addNullable": true,
            "removeNullable": false,
            "changeDefault": false
          },
          {
            "columnName": "destinoBaseId",
            "addNullable": true,
            "removeNullable": false,
            "changeDefault": false
          },
          {
            "columnName": "origemVeiculoId",
            "addNullable": true,
            "removeNullable": false,
            "changeDefault": false
          },
          {
            "columnName": "destinoVeiculoId",
            "addNullable": true,
            "removeNullable": false,
            "changeDefault": false
          }
        ],
        "addIndexes": [],
        "deleteIndexes": [],
        "addForeignKeys": [],
        "deleteForeignKeys": [],
        "warnings": []
      }
    },
    {
      "type": "createTable",
      "createTable": {
        "name": "requisicao_item",
        "dartName": "RequisicaoItem",
        "module": "organiza_metro",
        "schema": "public",
        "columns": [
          {
            "name": "id",
            "columnType": 6,
            "isNullable": false,
            "columnDefault": "nextval('requisicao_item_id_seq'::regclass)",
            "dartType": "int?"
          },
          {
            "name": "materialId",
            "columnType": 6,
            "isNullable": true,
            "dartType": "int?"
          },
          {
            "name": "ferramentaId",
            "columnType": 6,
            "isNullable": true,
            "dartType": "int?"
          },
          {
            "name": "quantidade",
            "columnType": 3,
            "isNullable": false,
            "dartType": "double"
          }
        ],
        "foreignKeys": [
          {
            "constraintName": "requisicao_item_fk_0",
            "columns": [
              "materialId"
            ],
            "referenceTable": "material",
            "referenceTableSchema": "public",
            "referenceColumns": [
              "id"
            ],
            "onUpdate": 3,
            "onDelete": 3
          },
          {
            "constraintName": "requisicao_item_fk_1",
            "columns": [
              "ferramentaId"
            ],
            "referenceTable": "ferramenta",
            "referenceTableSchema": "public",
            "referenceColumns": [
              "id"
            ],
            "onUpdate": 3,
            "onDelete": 3
          }
        ],
        "indexes": [
          {
            "indexName": "requisicao_item_pkey",
            "elements": [
              {
                "type": 0,
                "definition": "id"
              }
            ],
            "type": "btree",
            "isUnique": true,
            "isPrimary": true
          }
        ],
        "managed": true
      }
    }
  ],
  "warnings": [],
  "migrationApiVersion": 1
}